hyper2kvm/__init__.py
hyper2kvm/__main__.py
hyper2kvm/azure/__init__.py
hyper2kvm/azure/cleanup.py
hyper2kvm/azure/cli.py
hyper2kvm/azure/download.py
hyper2kvm/azure/exceptions.py
hyper2kvm/azure/models.py
hyper2kvm/azure/source.py
hyper2kvm/cli/__init__.py
hyper2kvm/cli/argument_parser.py
hyper2kvm/cli/daemon_ctl.py
hyper2kvm/cli/help_texts.py
hyper2kvm/cli/args/__init__.py
hyper2kvm/cli/args/builder.py
hyper2kvm/cli/args/groups.py
hyper2kvm/cli/args/helpers.py
hyper2kvm/cli/args/parser.py
hyper2kvm/cli/args/validators.py
hyper2kvm/config/__init__.py
hyper2kvm/config/config_loader.py
hyper2kvm/config/mapping_config.py
hyper2kvm/config/systemd_template.py
hyper2kvm/config/validation.py
hyper2kvm/converters/__init__.py
hyper2kvm/converters/disk_resizer.py
hyper2kvm/converters/fetch.py
hyper2kvm/converters/flatten.py
hyper2kvm/converters/extractors/__init__.py
hyper2kvm/converters/extractors/ami.py
hyper2kvm/converters/extractors/libvirt_xml.py
hyper2kvm/converters/extractors/ovf.py
hyper2kvm/converters/extractors/raw.py
hyper2kvm/converters/extractors/vhd.py
hyper2kvm/converters/qemu/__init__.py
hyper2kvm/converters/qemu/converter.py
hyper2kvm/core/__init__.py
hyper2kvm/core/cred.py
hyper2kvm/core/error_helpers.py
hyper2kvm/core/exceptions.py
hyper2kvm/core/file_ops.py
hyper2kvm/core/guest_identity.py
hyper2kvm/core/guest_inspector.py
hyper2kvm/core/guest_utils.py
hyper2kvm/core/guestfs_factory.py
hyper2kvm/core/list_utils.py
hyper2kvm/core/logger.py
hyper2kvm/core/logging_utils.py
hyper2kvm/core/metrics.py
hyper2kvm/core/optional_imports.py
hyper2kvm/core/progress.py
hyper2kvm/core/recovery_manager.py
hyper2kvm/core/retry.py
hyper2kvm/core/retry_enhanced.py
hyper2kvm/core/sanity_checker.py
hyper2kvm/core/utils.py
hyper2kvm/core/validation_suite.py
hyper2kvm/core/xml_utils.py
hyper2kvm/core/vmcraft/__init__.py
hyper2kvm/core/vmcraft/_utils.py
hyper2kvm/core/vmcraft/advanced_analysis.py
hyper2kvm/core/vmcraft/app_framework_detector.py
hyper2kvm-0.2.0.dist-info/licenses/LICENSE
hyper2kvm-0.2.0.dist-info/METADATA
hyper2kvm-0.2.0.dist-info/WHEEL
hyper2kvm-0.2.0.dist-info/entry_points.txt
hyper2kvm-0.2.0.dist-info/top_level.txt
hyper2kvm-0.2.0.dist-info/RECORD
