Metadata-Version: 2.4
Name: hyper2kvm
Version: 0.2.0
Summary: Production-Grade Hypervisor to KVM/QEMU Migration Toolkit
Author-email: Susant Sahani <ssahani@redhat.com>
Maintainer-email: Susant Sahani <ssahani@redhat.com>
License: LGPL-3.0-or-later
Project-URL: Homepage, https://github.com/ssahani/hyper2kvm
Project-URL: Documentation, https://github.com/ssahani/hyper2kvm/tree/main/docs
Project-URL: Repository, https://github.com/ssahani/hyper2kvm
Project-URL: Bug Tracker, https://github.com/ssahani/hyper2kvm/issues
Project-URL: Changelog, https://github.com/ssahani/hyper2kvm/releases
Keywords: kvm,qemu,virtualization,vm-migration,hypervisor,vmware,vsphere,azure,hyper-v,libvirt,cloud-migration
Classifier: Development Status :: 4 - Beta
Classifier: Intended Audience :: System Administrators
Classifier: Intended Audience :: Developers
Classifier: License :: OSI Approved :: GNU Lesser General Public License v3 or later (LGPLv3+)
Classifier: Operating System :: POSIX :: Linux
Classifier: Programming Language :: Python :: 3
Classifier: Programming Language :: Python :: 3.10
Classifier: Programming Language :: Python :: 3.11
Classifier: Programming Language :: Python :: 3.12
Classifier: Topic :: System :: Systems Administration
Classifier: Topic :: System :: Installation/Setup
Classifier: Topic :: Utilities
Classifier: Environment :: Console
Requires-Python: >=3.10
License-File: LICENSE
Requires-Dist: click>=8.0.0
Requires-Dist: pyyaml>=5.4.0
Requires-Dist: argcomplete>=2.0.0
Provides-Extra: ui
Requires-Dist: rich>=10.0.0; extra == "ui"
Provides-Extra: vsphere
Requires-Dist: pyvmomi>=7.0.0; extra == "vsphere"
Requires-Dist: requests>=2.25.0; extra == "vsphere"
Provides-Extra: azure
Requires-Dist: azure-identity>=1.10.0; extra == "azure"
Requires-Dist: azure-mgmt-compute>=29.0.0; extra == "azure"
Requires-Dist: azure-mgmt-network>=22.0.0; extra == "azure"
Requires-Dist: azure-mgmt-resource>=22.0.0; extra == "azure"
Requires-Dist: azure-storage-blob>=12.14.0; extra == "azure"
Requires-Dist: requests>=2.25.0; extra == "azure"
Provides-Extra: validation
Requires-Dist: pydantic>=2.5.0; extra == "validation"
Requires-Dist: pydantic-settings>=2.1.0; extra == "validation"
Provides-Extra: retry
Requires-Dist: tenacity>=8.2.0; extra == "retry"
Provides-Extra: daemon
Requires-Dist: watchdog>=3.0.0; extra == "daemon"
Provides-Extra: tui
Requires-Dist: textual>=0.47.0; extra == "tui"
Provides-Extra: async
Requires-Dist: httpx>=0.24.0; extra == "async"
Requires-Dist: httpx[http2]>=0.24.0; extra == "async"
Provides-Extra: enhanced
Requires-Dist: pydantic>=2.5.0; extra == "enhanced"
Requires-Dist: pydantic-settings>=2.1.0; extra == "enhanced"
Requires-Dist: tenacity>=8.2.0; extra == "enhanced"
Requires-Dist: watchdog>=3.0.0; extra == "enhanced"
Requires-Dist: textual>=0.47.0; extra == "enhanced"
Requires-Dist: httpx>=0.24.0; extra == "enhanced"
Requires-Dist: httpx[http2]>=0.24.0; extra == "enhanced"
Provides-Extra: full
Requires-Dist: rich>=10.0.0; extra == "full"
Requires-Dist: pyvmomi>=7.0.0; extra == "full"
Requires-Dist: requests>=2.25.0; extra == "full"
Requires-Dist: azure-identity>=1.10.0; extra == "full"
Requires-Dist: azure-mgmt-compute>=29.0.0; extra == "full"
Requires-Dist: azure-mgmt-network>=22.0.0; extra == "full"
Requires-Dist: azure-mgmt-resource>=22.0.0; extra == "full"
Requires-Dist: azure-storage-blob>=12.14.0; extra == "full"
Requires-Dist: pydantic>=2.5.0; extra == "full"
Requires-Dist: pydantic-settings>=2.1.0; extra == "full"
Requires-Dist: tenacity>=8.2.0; extra == "full"
Requires-Dist: watchdog>=3.0.0; extra == "full"
Requires-Dist: textual>=0.47.0; extra == "full"
Requires-Dist: httpx>=0.24.0; extra == "full"
Requires-Dist: httpx[http2]>=0.24.0; extra == "full"
Provides-Extra: dev
Requires-Dist: pytest>=7.0.0; extra == "dev"
Requires-Dist: pytest-cov>=3.0.0; extra == "dev"
Requires-Dist: pytest-asyncio>=0.21.0; extra == "dev"
Requires-Dist: black>=22.0.0; extra == "dev"
Requires-Dist: flake8>=4.0.0; extra == "dev"
Requires-Dist: mypy>=0.950; extra == "dev"
Requires-Dist: autoflake>=1.4; extra == "dev"
Requires-Dist: argcomplete>=2.0.0; extra == "dev"
Dynamic: license-file
